election_text_analysis/__init__.py
election_text_analysis/analyze.py
election_text_analysis/download_data.py
election_text_analysis/election_text_analysis.py
election_text_analysis/read_data.py
election_text_analysis-0.1.2.dist-info/LICENSE
election_text_analysis-0.1.2.dist-info/METADATA
election_text_analysis-0.1.2.dist-info/WHEEL
election_text_analysis-0.1.2.dist-info/RECORD
