Metadata-Version: 2.1
Name: election_text_analysis
Version: 0.1.2
Summary: Functions to load and analyzes open-ended data from the ANES election perception surveys conducted every 4 years
Home-page: https://github.com/QMSS-G5072-2023/election_text_analysis/tree/main
License: MIT
Author: Nikhila Anand
Requires-Python: >=3.11.5,<4.0.0
Classifier: License :: OSI Approved :: MIT License
Classifier: Programming Language :: Python :: 3
Project-URL: Documentation, https://election-text-analysis.readthedocs.io/en/latest/
Project-URL: Repository, https://github.com/QMSS-G5072-2023/election_text_analysis/tree/main
